iota_client_python-0.2.0_alpha.26.dist-info/METADATA
iota_client_python-0.2.0_alpha.26.dist-info/WHEEL
iota_client/__init__.py
iota_client/iota_client.pyd
iota_client_python-0.2.0_alpha.26.dist-info/RECORD
