Metadata-Version: 2.1
Name: iota-client-python
Version: 0.2.0_alpha.26
Summary: Client library of IOTA
Home-Page: https://iota.org
Author: Thoralf Müller <thoralf.mueller@iota.org, Antony Dikov <antoni.dikov@iota.org>, Bing-Yang Lin <bingyang.lin@iota.org>, Lucas Nogueira <lucas.nogueira@iota.org>, Nathan Jaremko <nathan@jaremko.ca>, Yu-Wei Wu <wusyong9104@gmail.com>
Author-Email: Thoralf Müller <thoralf.mueller@iota.org, Antony Dikov <antoni.dikov@iota.org>, Bing-Yang Lin <bingyang.lin@iota.org>, Lucas Nogueira <lucas.nogueira@iota.org>, Nathan Jaremko <nathan@jaremko.ca>, Yu-Wei Wu <wusyong9104@gmail.com>
License: Apache-2.0
